setup.py
rex/__init__.py
rex/rex.py
rex10ab.egg-info/PKG-INFO
rex10ab.egg-info/SOURCES.txt
rex10ab.egg-info/dependency_links.txt
rex10ab.egg-info/requires.txt
rex10ab.egg-info/top_level.txt