Metadata-Version: 1.0
Name: rex10ab
Version: 1.0
Summary: read smv file, write hdf file, etc.
Home-page: UNKNOWN
Author: Rui Xu
Author-email: rickxu2020@gmail.com
License: UNKNOWN
Platform: UNKNOWN
